[
{
"date": "2025-07-30 00:00:00",
"visitors": "1116",
"pageviews": "1590",
"visits": "1119",
"views_per_visit": "2.32",
"bounce_rate": "64",
"visit_duration": "480",
"scroll_depth": "52"
},
{
"date": "2025-07-30 01:00:00",
"visitors": "1634",
"pageviews": "2508",
"visits": "1641",
"views_per_visit": "2.68",
"bounce_rate": "66",
"visit_duration": "476",
"scroll_depth": "54"
},
{
"date": "2025-07-30 02:00:00",
"visitors": "1558",
"pageviews": "2560",
"visits": "1565",
"views_per_visit": "3.09",
"bounce_rate": "60",
"visit_duration": "626",
"scroll_depth": "59"
},
{
"date": "2025-07-30 03:00:00",
"visitors": "1276",
"pageviews": "2033",
"visits": "1284",
"views_per_visit": "2.9",
"bounce_rate": "61",
"visit_duration": "568",
"scroll_depth": "58"
},
{
"date": "2025-07-30 04:00:00",
"visitors": "1180",
"pageviews": "1711",
"visits": "1187",
"views_per_visit": "3.4",
"bounce_rate": "66",
"visit_duration": "607",
"scroll_depth": "49"
},
{
"date": "2025-07-30 05:00:00",
"visitors": "1462",
"pageviews": "2279",
"visits": "1479",
"views_per_visit": "3.15",
"bounce_rate": "61",
"visit_duration": "653",
"scroll_depth": "54"
},
{
"date": "2025-07-30 06:00:00",
"visitors": "1967",
"pageviews": "3287",
"visits": "1979",
"views_per_visit": "3.72",
"bounce_rate": "63",
"visit_duration": "730",
"scroll_depth": "52"
},
{
"date": "2025-07-30 07:00:00",
"visitors": "2178",
"pageviews": "3209",
"visits": "2191",
"views_per_visit": "2.84",
"bounce_rate": "64",
"visit_duration": "696",
"scroll_depth": "53"
},
{
"date": "2025-07-30 08:00:00",
"visitors": "2073",
"pageviews": "3290",
"visits": "2088",
"views_per_visit": "3.07",
"bounce_rate": "61",
"visit_duration": "621",
"scroll_depth": "56"
},
{
"date": "2025-07-30 09:00:00",
"visitors": "1841",
"pageviews": "2836",
"visits": "1853",
"views_per_visit": "2.98",
"bounce_rate": "61",
"visit_duration": "538",
"scroll_depth": "55"
},
{
"date": "2025-07-30 10:00:00",
"visitors": "1283",
"pageviews": "1907",
"visits": "1285",
"views_per_visit": "2.81",
"bounce_rate": "66",
"visit_duration": "466",
"scroll_depth": "54"
},
{
"date": "2025-07-30 11:00:00",
"visitors": "1426",
"pageviews": "2084",
"visits": "1428",
"views_per_visit": "2.59",
"bounce_rate": "64",
"visit_duration": "413",
"scroll_depth": "51"
},
{
"date": "2025-07-30 12:00:00",
"visitors": "1539",
"pageviews": "2316",
"visits": "1544",
"views_per_visit": "2.65",
"bounce_rate": "63",
"visit_duration": "479",
"scroll_depth": "54"
},
{
"date": "2025-07-30 13:00:00",
"visitors": "1723",
"pageviews": "2559",
"visits": "1731",
"views_per_visit": "2.64",
"bounce_rate": "66",
"visit_duration": "518",
"scroll_depth": "50"
},
{
"date": "2025-07-30 14:00:00",
"visitors": "1828",
"pageviews": "2802",
"visits": "1836",
"views_per_visit": "2.51",
"bounce_rate": "61",
"visit_duration": "464",
"scroll_depth": "53"
},
{
"date": "2025-07-30 15:00:00",
"visitors": "1642",
"pageviews": "2444",
"visits": "1648",
"views_per_visit": "2.53",
"bounce_rate": "64",
"visit_duration": "430",
"scroll_depth": "53"
},
{
"date": "2025-07-30 16:00:00",
"visitors": "1412",
"pageviews": "2158",
"visits": "1417",
"views_per_visit": "2.41",
"bounce_rate": "63",
"visit_duration": "334",
"scroll_depth": "53"
},
{
"date": "2025-07-30 17:00:00",
"visitors": "1131",
"pageviews": "1777",
"visits": "1163",
"views_per_visit": "2.51",
"bounce_rate": "66",
"visit_duration": "279",
"scroll_depth": "52"
},
{
"date": "2025-07-30 18:00:00",
"visitors": "937",
"pageviews": "1761",
"visits": "1170",
"views_per_visit": "2.66",
"bounce_rate": "67",
"visit_duration": "365",
"scroll_depth": "49"
},
{
"date": "2025-07-30 19:00:00",
"visitors": "715",
"pageviews": "1332",
"visits": "891",
"views_per_visit": "2.85",
"bounce_rate": "60",
"visit_duration": "484",
"scroll_depth": "53"
},
{
"date": "2025-07-30 20:00:00",
"visitors": "720",
"pageviews": "1423",
"visits": "921",
"views_per_visit": "2.76",
"bounce_rate": "62",
"visit_duration": "407",
"scroll_depth": "54"
},
{
"date": "2025-07-30 21:00:00",
"visitors": "636",
"pageviews": "1120",
"visits": "781",
"views_per_visit": "2.7",
"bounce_rate": "67",
"visit_duration": "302",
"scroll_depth": "51"
},
{
"date": "2025-07-30 22:00:00",
"visitors": "546",
"pageviews": "1024",
"visits": "676",
"views_per_visit": "2.46",
"bounce_rate": "62",
"visit_duration": "392",
"scroll_depth": "52"
},
{
"date": "2025-07-30 23:00:00",
"visitors": "615",
"pageviews": "1067",
"visits": "744",
"views_per_visit": "4.68",
"bounce_rate": "69",
"visit_duration": "376",
"scroll_depth": "49"
}
]