[
{
"name": "Chrome",
"visitors": "1221"
},
{
"name": "Microsoft Edge",
"visitors": "489"
},
{
"name": "Firefox",
"visitors": "204"
},
{
"name": "Safari",
"visitors": "116"
},
{
"name": "Opera",
"visitors": "43"
},
{
"name": "Yandex Browser",
"visitors": "40"
},
{
"name": "Mobile App",
"visitors": "37"
},
{
"name": "QQ Browser",
"visitors": "14"
},
{
"name": "Quark",
"visitors": "12"
},
{
"name": "Smart Lenovo Browser",
"visitors": "11"
},
{
"name": "UC Browser",
"visitors": "8"
},
{
"name": "Samsung Browser",
"visitors": "4"
},
{
"name": "SberBrowser",
"visitors": "4"
},
{
"name": "MIUI Browser",
"visitors": "3"
},
{
"name": "Opera GX",
"visitors": "3"
},
{
"name": "Sogou Explorer",
"visitors": "3"
},
{
"name": "Brave",
"visitors": "2"
},
{
"name": "Huawei Browser",
"visitors": "2"
},
{
"name": "Norton Private Browser",
"visitors": "2"
},
{
"name": "vivo Browser",
"visitors": "2"
},
{
"name": "(not set)",
"visitors": "1"
},
{
"name": "Avast Secure Browser",
"visitors": "1"
},
{
"name": "Huawei Browser Mobile",
"visitors": "1"
},
{
"name": "SeaMonkey",
"visitors": "1"
}
]