[
{
"name": "Maharashtra",
"visitors": "11185"
},
{
"name": "England",
"visitors": "9370"
},
{
"name": "Tamil Nadu",
"visitors": "8770"
},
{
"name": "California",
"visitors": "7759"
},
{
"name": "Karnataka",
"visitors": "7750"
},
{
"name": "Tokyo",
"visitors": "5797"
},
{
"name": "S\u00e3o Paulo",
"visitors": "5714"
},
{
"name": "Delhi",
"visitors": "5628"
},
{
"name": "Guangdong",
"visitors": "5522"
},
{
"name": "Telang\u0101na",
"visitors": "5116"
},
{
"name": "Uttar Pradesh",
"visitors": "4223"
},
{
"name": "Texas",
"visitors": "4056"
},
{
"name": "Punjab",
"visitors": "3854"
},
{
"name": "\u00cele-de-France",
"visitors": "3835"
},
{
"name": "Seoul",
"visitors": "3756"
},
{
"name": "Ho Chi Minh City",
"visitors": "3701"
},
{
"name": "Hanoi",
"visitors": "3479"
},
{
"name": "Jakarta",
"visitors": "3391"
},
{
"name": "Beijing",
"visitors": "3368"
},
{
"name": "Moscow",
"visitors": "3309"
},
{
"name": "Ontario",
"visitors": "3116"
},
{
"name": "New York",
"visitors": "3061"
},
{
"name": "Shanghai",
"visitors": "2992"
},
{
"name": "Kerala",
"visitors": "2808"
},
{
"name": "Jiangsu",
"visitors": "2803"
},
{
"name": "Zhejiang",
"visitors": "2768"
},
{
"name": "Istanbul",
"visitors": "2691"
},
{
"name": "Virginia",
"visitors": "2671"
},
{
"name": "Shandong",
"visitors": "2514"
},
{
"name": "Florida",
"visitors": "2356"
},
{
"name": "Madrid Autonomous Community",
"visitors": "2354"
},
{
"name": "West Bengal",
"visitors": "2286"
},
{
"name": "Hesse",
"visitors": "2279"
},
{
"name": "Ciudad de Mexico",
"visitors": "2241"
},
{
"name": "North Rhine-Westphalia",
"visitors": "2173"
},
{
"name": "Gyeonggi",
"visitors": "2169"
},
{
"name": "North Holland",
"visitors": "2157"
},
{
"name": "Tashkent",
"visitors": "2150"
},
{
"name": "Gujarat",
"visitors": "2134"
},
{
"name": "Illinois",
"visitors": "2129"
},
{
"name": "Sichuan",
"visitors": "2120"
},
{
"name": "Madhya Pradesh",
"visitors": "2031"
},
{
"name": "Lima",
"visitors": "1963"
},
{
"name": "Lombardy",
"visitors": "1944"
},
{
"name": "Capital District",
"visitors": "1880"
},
{
"name": "Washington",
"visitors": "1820"
},
{
"name": "Bavaria",
"visitors": "1738"
},
{
"name": "West Java",
"visitors": "1686"
},
{
"name": "Santiago Metropolitan",
"visitors": "1667"
},
{
"name": "Metro Manila",
"visitors": "1664"
},
{
"name": "Cairo",
"visitors": "1637"
},
{
"name": "Henan",
"visitors": "1635"
},
{
"name": "Mazovia",
"visitors": "1601"
},
{
"name": "Georgia",
"visitors": "1578"
},
{
"name": "Bangkok",
"visitors": "1565"
},
{
"name": "Rajasthan",
"visitors": "1550"
},
{
"name": "Nairobi County",
"visitors": "1546"
},
{
"name": "Taipei",
"visitors": "1545"
},
{
"name": "Sindh",
"visitors": "1541"
},
{
"name": "Rio de Janeiro",
"visitors": "1529"
},
{
"name": "Buenos Aires Province",
"visitors": "1506"
},
{
"name": "New South Wales",
"visitors": "1466"
},
{
"name": "Minas Gerais",
"visitors": "1458"
},
{
"name": "Catalonia",
"visitors": "1428"
},
{
"name": "Hubei",
"visitors": "1427"
},
{
"name": "New Jersey",
"visitors": "1420"
},
{
"name": "Haryana",
"visitors": "1395"
},
{
"name": "Quebec",
"visitors": "1352"
},
{
"name": "Osaka",
"visitors": "1324"
},
{
"name": "Shaanxi",
"visitors": "1297"
},
{
"name": "Dubai",
"visitors": "1296"
},
{
"name": "Antioquia",
"visitors": "1293"
},
{
"name": "Baden-W\u00fcrttemberg",
"visitors": "1265"
},
{
"name": "Massachusetts",
"visitors": "1261"
},
{
"name": "Andhra Pradesh",
"visitors": "1250"
},
{
"name": "North Carolina",
"visitors": "1242"
},
{
"name": "Saint Petersburg",
"visitors": "1154"
},
{
"name": "Ohio",
"visitors": "1143"
},
{
"name": "Pennsylvania",
"visitors": "1142"
},
{
"name": "Hunan",
"visitors": "1140"
},
{
"name": "Kuala Lumpur",
"visitors": "1123"
},
{
"name": "Western",
"visitors": "1099"
},
{
"name": "Lagos",
"visitors": "1094"
},
{
"name": "Mexico State",
"visitors": "1065"
},
{
"name": "Riyadh",
"visitors": "1054"
},
{
"name": "East Java",
"visitors": "1045"
},
{
"name": "Chongqing",
"visitors": "1025"
},
{
"name": "Flanders",
"visitors": "1018"
},
{
"name": "Leinster",
"visitors": "1007"
},
{
"name": "Fujian",
"visitors": "1006"
},
{
"name": "New Taipei",
"visitors": "1006"
},
{
"name": "Lazio",
"visitors": "1005"
},
{
"name": "Paran\u00e1",
"visitors": "1003"
},
{
"name": "Bihar",
"visitors": "990"
},
{
"name": "Gauteng",
"visitors": "989"
},
{
"name": "Kyiv",
"visitors": "984"
},
{
"name": "Ankara",
"visitors": "974"
},
{
"name": "Victoria",
"visitors": "962"
},
{
"name": "Tel Aviv",
"visitors": "962"
},
{
"name": "Maryland",
"visitors": "938"
},
{
"name": "Central Java",
"visitors": "925"
},
{
"name": "South Holland",
"visitors": "914"
},
{
"name": "Selangor",
"visitors": "908"
},
{
"name": "Punjab",
"visitors": "903"
},
{
"name": "Michigan",
"visitors": "899"
},
{
"name": "Colorado",
"visitors": "898"
},
{
"name": "Makkah",
"visitors": "892"
},
{
"name": "Andalusia",
"visitors": "885"
},
{
"name": "Auvergne-Rh\u00f4ne-Alpes",
"visitors": "869"
},
{
"name": "Z\u00fcrich",
"visitors": "858"
},
{
"name": "Brussels",
"visitors": "851"
},
{
"name": "British Columbia",
"visitors": "850"
},
{
"name": "Arizona",
"visitors": "847"
},
{
"name": "Rio Grande do Sul",
"visitors": "845"
},
{
"name": "Stockholm",
"visitors": "839"
},
{
"name": "Lisbon",
"visitors": "834"
},
{
"name": "Vienna",
"visitors": "828"
},
{
"name": "Dhaka Division",
"visitors": "825"
},
{
"name": "Oregon",
"visitors": "820"
},
{
"name": "Jharkhand",
"visitors": "809"
},
{
"name": "Hormozgan",
"visitors": "803"
},
{
"name": "Odisha",
"visitors": "790"
},
{
"name": "Prague",
"visitors": "786"
},
{
"name": "Mekn\u00e8s-Tafilalet",
"visitors": "786"
},
{
"name": "Amman",
"visitors": "784"
},
{
"name": "Calabarzon",
"visitors": "731"
},
{
"name": "Uusimaa",
"visitors": "727"
},
{
"name": "Chandigarh",
"visitors": "726"
},
{
"name": "Attica",
"visitors": "715"
},
{
"name": "Santa Catarina",
"visitors": "713"
},
{
"name": "Lower Saxony",
"visitors": "711"
},
{
"name": "Kanagawa",
"visitors": "711"
},
{
"name": "Greater Accra",
"visitors": "703"
},
{
"name": "Valencian Community",
"visitors": "701"
},
{
"name": "Tianjin",
"visitors": "699"
},
{
"name": "Provence-Alpes-C\u00f4te-d'Azur",
"visitors": "698"
},
{
"name": "Islamabad",
"visitors": "688"
},
{
"name": "Taichung",
"visitors": "678"
},
{
"name": "Hebei",
"visitors": "676"
},
{
"name": "Cear\u00e1",
"visitors": "673"
},
{
"name": "Berlin",
"visitors": "660"
},
{
"name": "Budapest",
"visitors": "659"
},
{
"name": "Anhui",
"visitors": "653"
},
{
"name": "Alberta",
"visitors": "652"
},
{
"name": "Jalisco",
"visitors": "646"
},
{
"name": "Almaty City",
"visitors": "640"
},
{
"name": "Abu Dhabi",
"visitors": "639"
},
{
"name": "Moscow Province",
"visitors": "636"
},
{
"name": "Tunis",
"visitors": "633"
},
{
"name": "Federal District",
"visitors": "631"
},
{
"name": "Piedmont",
"visitors": "615"
},
{
"name": "Indiana",
"visitors": "606"
},
{
"name": "Kaohsiung",
"visitors": "603"
},
{
"name": "Bahia",
"visitors": "601"
},
{
"name": "Utah",
"visitors": "601"
},
{
"name": "Baku",
"visitors": "599"
},
{
"name": "Scotland",
"visitors": "598"
},
{
"name": "Pichincha",
"visitors": "595"
},
{
"name": "Uttar\u0101khand",
"visitors": "592"
},
{
"name": "Aichi",
"visitors": "592"
},
{
"name": "Missouri",
"visitors": "582"
},
{
"name": "Krasnodar Krai",
"visitors": "554"
},
{
"name": "Iowa",
"visitors": "551"
},
{
"name": "Occitanie",
"visitors": "550"
},
{
"name": "Tennessee",
"visitors": "549"
},
{
"name": "Minsk",
"visitors": "546"
},
{
"name": "Pernambuco",
"visitors": "542"
},
{
"name": "Assam",
"visitors": "542"
},
{
"name": "Puebla",
"visitors": "538"
},
{
"name": "Izmir",
"visitors": "538"
},
{
"name": "Central Luzon",
"visitors": "536"
},
{
"name": "Guayas",
"visitors": "530"
},
{
"name": "Province 3",
"visitors": "526"
},
{
"name": "Nuevo Le\u00f3n",
"visitors": "525"
},
{
"name": "Taoyuan",
"visitors": "515"
},
{
"name": "Grand-Est",
"visitors": "514"
},
{
"name": "Minnesota",
"visitors": "512"
},
{
"name": "Incheon",
"visitors": "509"
},
{
"name": "Saxony",
"visitors": "507"
},
{
"name": "Liaoning",
"visitors": "506"
},
{
"name": "Emilia-Romagna",
"visitors": "503"
},
{
"name": "Hauts-de-France",
"visitors": "502"
},
{
"name": "Capital Region",
"visitors": "496"
},
{
"name": "Queensland",
"visitors": "493"
},
{
"name": "Sverdlovsk",
"visitors": "492"
},
{
"name": "Tatarstan",
"visitors": "491"
},
{
"name": "Campania",
"visitors": "482"
},
{
"name": "Yogyakarta",
"visitors": "481"
},
{
"name": "Veneto",
"visitors": "481"
},
{
"name": "San Jos\u00e9",
"visitors": "479"
},
{
"name": "Phnom Penh",
"visitors": "472"
},
{
"name": "Astana",
"visitors": "471"
},
{
"name": "Wisconsin",
"visitors": "468"
},
{
"name": "Bishkek",
"visitors": "464"
},
{
"name": "Tbilisi",
"visitors": "461"
},
{
"name": "Goi\u00e1s",
"visitors": "460"
},
{
"name": "Eastern",
"visitors": "459"
},
{
"name": "Lesser Poland",
"visitors": "446"
},
{
"name": "Busan",
"visitors": "441"
},
{
"name": "Lima Region",
"visitors": "438"
},
{
"name": "Porto",
"visitors": "437"
},
{
"name": "Samara",
"visitors": "432"
},
{
"name": "Bucharest",
"visitors": "426"
},
{
"name": "Beograd",
"visitors": "421"
},
{
"name": "Greater Poland",
"visitors": "419"
},
{
"name": "Valle del Cauca",
"visitors": "417"
},
{
"name": "Gwangju City",
"visitors": "409"
},
{
"name": "Rostov",
"visitors": "408"
},
{
"name": "Nouvelle-Aquitaine",
"visitors": "407"
},
{
"name": "Addis Ababa",
"visitors": "405"
},
{
"name": "Federal Capital Territory",
"visitors": "396"
},
{
"name": "Hamburg",
"visitors": "395"
},
{
"name": "Abidjan",
"visitors": "393"
},
{
"name": "San Salvador",
"visitors": "393"
},
{
"name": "Muscat",
"visitors": "391"
},
{
"name": "Kigali",
"visitors": "390"
},
{
"name": "Veracruz",
"visitors": "381"
},
{
"name": "Alabama",
"visitors": "381"
},
{
"name": "Guizhou",
"visitors": "380"
},
{
"name": "Yunnan",
"visitors": "377"
},
{
"name": "Saitama",
"visitors": "376"
},
{
"name": "Chelyabinsk",
"visitors": "376"
},
{
"name": "South Carolina",
"visitors": "376"
},
{
"name": "Khyber Pakhtunkhwa",
"visitors": "375"
},
{
"name": "Pays-de-la-Loire",
"visitors": "372"
},
{
"name": "Buenos Aires",
"visitors": "371"
},
{
"name": "Chiba",
"visitors": "368"
},
{
"name": "Doha",
"visitors": "368"
},
{
"name": "Central Visayas",
"visitors": "366"
},
{
"name": "Par\u00e1",
"visitors": "363"
},
{
"name": "Oriental",
"visitors": "363"
},
{
"name": "Lvivshchyna",
"visitors": "363"
},
{
"name": "Oslo",
"visitors": "356"
},
{
"name": "Central",
"visitors": "355"
},
{
"name": "Wallonia",
"visitors": "352"
},
{
"name": "Da Nang",
"visitors": "352"
},
{
"name": "La Paz",
"visitors": "350"
},
{
"name": "Connecticut",
"visitors": "350"
},
{
"name": "Bashkortostan",
"visitors": "348"
},
{
"name": "Western Cape",
"visitors": "345"
},
{
"name": "Sofia",
"visitors": "339"
},
{
"name": "Giza",
"visitors": "336"
},
{
"name": "Silesia",
"visitors": "335"
},
{
"name": "Novosibirsk",
"visitors": "334"
},
{
"name": "Distrito Nacional",
"visitors": "333"
},
{
"name": "V\u00e4stra G\u00f6taland",
"visitors": "333"
},
{
"name": "Baghdad",
"visitors": "332"
},
{
"name": "Nevada",
"visitors": "332"
},
{
"name": "Guatemala",
"visitors": "331"
},
{
"name": "South Sulawesi",
"visitors": "331"
},
{
"name": "Western Australia",
"visitors": "328"
},
{
"name": "Rabat-Sal\u00e9-Zemmour-Zaer",
"visitors": "326"
},
{
"name": "Riga",
"visitors": "324"
},
{
"name": "Jiangxi",
"visitors": "322"
},
{
"name": "Daegu",
"visitors": "319"
},
{
"name": "Auckland",
"visitors": "317"
},
{
"name": "Sicily",
"visitors": "316"
},
{
"name": "Lower Silesia",
"visitors": "313"
},
{
"name": "Arkansas",
"visitors": "313"
},
{
"name": "Ulaanbaatar",
"visitors": "311"
},
{
"name": "Oyo",
"visitors": "310"
},
{
"name": "Rhineland-Palatinate",
"visitors": "309"
},
{
"name": "Tuscany",
"visitors": "308"
},
{
"name": "Nizhny Novgorod",
"visitors": "308"
},
{
"name": "Gansu",
"visitors": "305"
},
{
"name": "Kentucky",
"visitors": "305"
},
{
"name": "Algiers",
"visitors": "304"
},
{
"name": "Bratislava",
"visitors": "304"
},
{
"name": "Amazonas",
"visitors": "303"
},
{
"name": "Bursa",
"visitors": "303"
},
{
"name": "Guanajuato",
"visitors": "299"
},
{
"name": "Kwai Tsing New Territories",
"visitors": "297"
},
{
"name": "Quer\u00e9taro",
"visitors": "297"
},
{
"name": "Oklahoma",
"visitors": "296"
},
{
"name": "North Brabant",
"visitors": "295"
},
{
"name": "Dnipropetrovshchyna",
"visitors": "293"
},
{
"name": "Banten",
"visitors": "288"
},
{
"name": "C\u00f3rdoba",
"visitors": "287"
},
{
"name": "Cundinamarca",
"visitors": "287"
},
{
"name": "Central",
"visitors": "286"
},
{
"name": "Washington DC",
"visitors": "285"
},
{
"name": "Louisiana",
"visitors": "285"
},
{
"name": "Wales",
"visitors": "283"
},
{
"name": "Antalya",
"visitors": "279"
},
{
"name": "Baja California",
"visitors": "277"
},
{
"name": "Atl\u00e1ntico",
"visitors": "275"
},
{
"name": "Chihuahua",
"visitors": "271"
},
{
"name": "Riau",
"visitors": "270"
},
{
"name": "Montevideo",
"visitors": "269"
},
{
"name": "South Gyeongsang",
"visitors": "268"
},
{
"name": "Daejeon",
"visitors": "267"
},
{
"name": "Harare",
"visitors": "267"
},
{
"name": "Sharjah",
"visitors": "266"
},
{
"name": "Vilnius County",
"visitors": "262"
},
{
"name": "Kowloon City Kowloon",
"visitors": "259"
},
{
"name": "Davao",
"visitors": "257"
},
{
"name": "Pomerania",
"visitors": "256"
},
{
"name": "Kansas",
"visitors": "256"
},
{
"name": "Para\u00edba",
"visitors": "252"
},
{
"name": "Utrecht",
"visitors": "251"
}
]