[
{
"date": "2025-07-24 00:00:00",
"visitors": "1195",
"pageviews": "1704",
"visits": "1215",
"views_per_visit": "2.43",
"bounce_rate": "68",
"visit_duration": "421",
"scroll_depth": "52"
},
{
"date": "2025-07-24 01:00:00",
"visitors": "1401",
"pageviews": "2161",
"visits": "1406",
"views_per_visit": "2.69",
"bounce_rate": "62",
"visit_duration": "508",
"scroll_depth": "53"
},
{
"date": "2025-07-24 02:00:00",
"visitors": "1547",
"pageviews": "2344",
"visits": "1555",
"views_per_visit": "3.67",
"bounce_rate": "61",
"visit_duration": "551",
"scroll_depth": "57"
},
{
"date": "2025-07-24 03:00:00",
"visitors": "1304",
"pageviews": "2540",
"visits": "1310",
"views_per_visit": "4.57",
"bounce_rate": "61",
"visit_duration": "585",
"scroll_depth": "56"
},
{
"date": "2025-07-24 04:00:00",
"visitors": "1117",
"pageviews": "1681",
"visits": "1127",
"views_per_visit": "4.09",
"bounce_rate": "65",
"visit_duration": "586",
"scroll_depth": "50"
},
{
"date": "2025-07-24 05:00:00",
"visitors": "1485",
"pageviews": "2431",
"visits": "1496",
"views_per_visit": "4.2",
"bounce_rate": "61",
"visit_duration": "679",
"scroll_depth": "53"
},
{
"date": "2025-07-24 06:00:00",
"visitors": "1772",
"pageviews": "2937",
"visits": "1776",
"views_per_visit": "4.5",
"bounce_rate": "56",
"visit_duration": "902",
"scroll_depth": "55"
},
{
"date": "2025-07-24 07:00:00",
"visitors": "1864",
"pageviews": "2941",
"visits": "1873",
"views_per_visit": "4.36",
"bounce_rate": "58",
"visit_duration": "942",
"scroll_depth": "55"
},
{
"date": "2025-07-24 08:00:00",
"visitors": "1868",
"pageviews": "2826",
"visits": "1875",
"views_per_visit": "3.6",
"bounce_rate": "59",
"visit_duration": "854",
"scroll_depth": "56"
},
{
"date": "2025-07-24 09:00:00",
"visitors": "1764",
"pageviews": "2694",
"visits": "1772",
"views_per_visit": "3.28",
"bounce_rate": "62",
"visit_duration": "721",
"scroll_depth": "55"
},
{
"date": "2025-07-24 10:00:00",
"visitors": "1448",
"pageviews": "2320",
"visits": "1451",
"views_per_visit": "2.9",
"bounce_rate": "60",
"visit_duration": "548",
"scroll_depth": "56"
},
{
"date": "2025-07-24 11:00:00",
"visitors": "1358",
"pageviews": "2211",
"visits": "1363",
"views_per_visit": "3.15",
"bounce_rate": "64",
"visit_duration": "638",
"scroll_depth": "55"
},
{
"date": "2025-07-24 12:00:00",
"visitors": "1564",
"pageviews": "2491",
"visits": "1568",
"views_per_visit": "3.25",
"bounce_rate": "60",
"visit_duration": "754",
"scroll_depth": "55"
},
{
"date": "2025-07-24 13:00:00",
"visitors": "1698",
"pageviews": "2736",
"visits": "1705",
"views_per_visit": "3.1",
"bounce_rate": "61",
"visit_duration": "648",
"scroll_depth": "54"
},
{
"date": "2025-07-24 14:00:00",
"visitors": "1679",
"pageviews": "2527",
"visits": "1693",
"views_per_visit": "2.54",
"bounce_rate": "64",
"visit_duration": "482",
"scroll_depth": "52"
},
{
"date": "2025-07-24 15:00:00",
"visitors": "1569",
"pageviews": "2442",
"visits": "1575",
"views_per_visit": "2.5",
"bounce_rate": "63",
"visit_duration": "469",
"scroll_depth": "51"
},
{
"date": "2025-07-24 16:00:00",
"visitors": "1315",
"pageviews": "1892",
"visits": "1318",
"views_per_visit": "2.31",
"bounce_rate": "64",
"visit_duration": "487",
"scroll_depth": "52"
},
{
"date": "2025-07-24 17:00:00",
"visitors": "1138",
"pageviews": "1662",
"visits": "1144",
"views_per_visit": "2.44",
"bounce_rate": "65",
"visit_duration": "414",
"scroll_depth": "53"
},
{
"date": "2025-07-24 18:00:00",
"visitors": "962",
"pageviews": "1513",
"visits": "969",
"views_per_visit": "2.49",
"bounce_rate": "64",
"visit_duration": "374",
"scroll_depth": "55"
},
{
"date": "2025-07-24 19:00:00",
"visitors": "933",
"pageviews": "1407",
"visits": "937",
"views_per_visit": "2.41",
"bounce_rate": "60",
"visit_duration": "347",
"scroll_depth": "57"
},
{
"date": "2025-07-24 20:00:00",
"visitors": "857",
"pageviews": "1380",
"visits": "862",
"views_per_visit": "2.64",
"bounce_rate": "64",
"visit_duration": "363",
"scroll_depth": "53"
},
{
"date": "2025-07-24 21:00:00",
"visitors": "758",
"pageviews": "1237",
"visits": "763",
"views_per_visit": "2.86",
"bounce_rate": "59",
"visit_duration": "586",
"scroll_depth": "52"
},
{
"date": "2025-07-24 22:00:00",
"visitors": "738",
"pageviews": "1196",
"visits": "740",
"views_per_visit": "2.92",
"bounce_rate": "58",
"visit_duration": "553",
"scroll_depth": "52"
},
{
"date": "2025-07-24 23:00:00",
"visitors": "728",
"pageviews": "1162",
"visits": "729",
"views_per_visit": "3.94",
"bounce_rate": "69",
"visit_duration": "364",
"scroll_depth": "50"
}
]