[
{
"property": "url",
"value": "(none)",
"visitors": "101",
"events": "218",
"percentage": "99.0"
},
{
"property": "url",
"value": "https://www.python.org/",
"visitors": "8",
"events": "9",
"percentage": "7.8"
},
{
"property": "url",
"value": "https://peps.python.org/pep-0011/",
"visitors": "1",
"events": "1",
"percentage": "1.0"
},
{
"property": "url",
"value": "https://peps.python.org/pep-0596/",
"visitors": "1",
"events": "1",
"percentage": "1.0"
},
{
"property": "url",
"value": "https://wiki.python.org/moin/BeginnersGuide",
"visitors": "1",
"events": "1",
"percentage": "1.0"
}
]