[
{
"name": "Tokyo",
"visitors": "118"
},
{
"name": "Kanagawa",
"visitors": "24"
},
{
"name": "Osaka",
"visitors": "22"
},
{
"name": "Aichi",
"visitors": "11"
},
{
"name": "Saitama",
"visitors": "9"
},
{
"name": "Hyogo",
"visitors": "6"
},
{
"name": "Fukuoka",
"visitors": "4"
},
{
"name": "Miyagi",
"visitors": "3"
},
{
"name": "Gunma",
"visitors": "3"
},
{
"name": "Chiba",
"visitors": "3"
},
{
"name": "Henan",
"visitors": "2"
},
{
"name": "Jiangsu",
"visitors": "2"
},
{
"name": "Aomori",
"visitors": "2"
},
{
"name": "Tochigi",
"visitors": "2"
},
{
"name": "Niigata",
"visitors": "2"
},
{
"name": "Nara",
"visitors": "2"
},
{
"name": "Miyazaki",
"visitors": "2"
},
{
"name": "Taichung",
"visitors": "2"
},
{
"name": "Texas",
"visitors": "2"
},
{
"name": "Guangdong",
"visitors": "1"
},
{
"name": "Hebei",
"visitors": "1"
},
{
"name": "Uusimaa",
"visitors": "1"
},
{
"name": "Yamagata",
"visitors": "1"
},
{
"name": "Ibaraki",
"visitors": "1"
},
{
"name": "Toyama",
"visitors": "1"
},
{
"name": "Nagano",
"visitors": "1"
},
{
"name": "Shizuoka",
"visitors": "1"
},
{
"name": "Shiga",
"visitors": "1"
},
{
"name": "Kyoto",
"visitors": "1"
},
{
"name": "Okayama",
"visitors": "1"
},
{
"name": "Hiroshima",
"visitors": "1"
},
{
"name": "Tokushima",
"visitors": "1"
},
{
"name": "Kagawa",
"visitors": "1"
},
{
"name": "Saga",
"visitors": "1"
},
{
"name": "Oita",
"visitors": "1"
},
{
"name": "Okinawa",
"visitors": "1"
}
]