[
{
"date": "2025-11-21 00:00:00",
"visitors": "43893",
"pageviews": "44968",
"visits": "43989",
"views_per_visit": "1.07",
"bounce_rate": "97",
"visit_duration": "49"
},
{
"date": "2025-11-21 01:00:00",
"visitors": "44142",
"pageviews": "45179",
"visits": "44250",
"views_per_visit": "1.06",
"bounce_rate": "97",
"visit_duration": "45"
},
{
"date": "2025-11-21 02:00:00",
"visitors": "44482",
"pageviews": "45755",
"visits": "44581",
"views_per_visit": "1.07",
"bounce_rate": "96",
"visit_duration": "46"
},
{
"date": "2025-11-21 03:00:00",
"visitors": "44700",
"pageviews": "45821",
"visits": "44787",
"views_per_visit": "1.06",
"bounce_rate": "97",
"visit_duration": "41"
},
{
"date": "2025-11-21 04:00:00",
"visitors": "45046",
"pageviews": "46063",
"visits": "45130",
"views_per_visit": "1.05",
"bounce_rate": "97",
"visit_duration": "31"
},
{
"date": "2025-11-21 05:00:00",
"visitors": "45466",
"pageviews": "46580",
"visits": "45560",
"views_per_visit": "1.05",
"bounce_rate": "97",
"visit_duration": "32"
},
{
"date": "2025-11-21 06:00:00",
"visitors": "44012",
"pageviews": "44860",
"visits": "44093",
"views_per_visit": "1.04",
"bounce_rate": "97",
"visit_duration": "28"
},
{
"date": "2025-11-21 07:00:00",
"visitors": "45024",
"pageviews": "46015",
"visits": "45106",
"views_per_visit": "1.05",
"bounce_rate": "97",
"visit_duration": "28"
},
{
"date": "2025-11-21 08:00:00",
"visitors": "45543",
"pageviews": "46576",
"visits": "45619",
"views_per_visit": "1.05",
"bounce_rate": "97",
"visit_duration": "28"
},
{
"date": "2025-11-21 09:00:00",
"visitors": "45660",
"pageviews": "46602",
"visits": "45739",
"views_per_visit": "1.04",
"bounce_rate": "97",
"visit_duration": "28"
},
{
"date": "2025-11-21 10:00:00",
"visitors": "45734",
"pageviews": "46717",
"visits": "45830",
"views_per_visit": "1.04",
"bounce_rate": "97",
"visit_duration": "27"
},
{
"date": "2025-11-21 11:00:00",
"visitors": "44956",
"pageviews": "45881",
"visits": "45030",
"views_per_visit": "1.04",
"bounce_rate": "97",
"visit_duration": "28"
},
{
"date": "2025-11-21 12:00:00",
"visitors": "45150",
"pageviews": "46046",
"visits": "45238",
"views_per_visit": "1.05",
"bounce_rate": "97",
"visit_duration": "30"
},
{
"date": "2025-11-21 13:00:00",
"visitors": "44767",
"pageviews": "45646",
"visits": "44849",
"views_per_visit": "1.05",
"bounce_rate": "97",
"visit_duration": "30"
},
{
"date": "2025-11-21 14:00:00",
"visitors": "44542",
"pageviews": "45385",
"visits": "44625",
"views_per_visit": "1.04",
"bounce_rate": "97",
"visit_duration": "29"
},
{
"date": "2025-11-21 15:00:00",
"visitors": "44567",
"pageviews": "45338",
"visits": "44635",
"views_per_visit": "1.03",
"bounce_rate": "97",
"visit_duration": "25"
},
{
"date": "2025-11-21 16:00:00",
"visitors": "44471",
"pageviews": "45247",
"visits": "44558",
"views_per_visit": "1.03",
"bounce_rate": "97",
"visit_duration": "25"
},
{
"date": "2025-11-21 17:00:00",
"visitors": "44483",
"pageviews": "45303",
"visits": "44560",
"views_per_visit": "1.04",
"bounce_rate": "97",
"visit_duration": "28"
},
{
"date": "2025-11-21 18:00:00",
"visitors": "44170",
"pageviews": "44991",
"visits": "44270",
"views_per_visit": "1.04",
"bounce_rate": "97",
"visit_duration": "29"
},
{
"date": "2025-11-21 19:00:00",
"visitors": "44353",
"pageviews": "45072",
"visits": "44425",
"views_per_visit": "1.04",
"bounce_rate": "98",
"visit_duration": "27"
},
{
"date": "2025-11-21 20:00:00",
"visitors": "44079",
"pageviews": "44879",
"visits": "44165",
"views_per_visit": "1.04",
"bounce_rate": "97",
"visit_duration": "28"
},
{
"date": "2025-11-21 21:00:00",
"visitors": "44256",
"pageviews": "44968",
"visits": "44345",
"views_per_visit": "1.04",
"bounce_rate": "98",
"visit_duration": "26"
},
{
"date": "2025-11-21 22:00:00",
"visitors": "44083",
"pageviews": "44882",
"visits": "44173",
"views_per_visit": "1.03",
"bounce_rate": "98",
"visit_duration": "22"
},
{
"date": "2025-11-21 23:00:00",
"visitors": "9",
"pageviews": "9",
"visits": "9",
"views_per_visit": "1.0",
"bounce_rate": "100",
"visit_duration": "0"
}
]