[
{
"name": "Bogot\u00e1",
"visitors": "217"
},
{
"name": "Madrid",
"visitors": "206"
},
{
"name": "Lima",
"visitors": "147"
},
{
"name": "Santiago",
"visitors": "144"
},
{
"name": "N/A",
"visitors": "88"
},
{
"name": "Medell\u00edn",
"visitors": "78"
},
{
"name": "Barcelona",
"visitors": "53"
},
{
"name": "Buenos Aires",
"visitors": "53"
},
{
"name": "Mexico City",
"visitors": "44"
},
{
"name": "Quito",
"visitors": "40"
},
{
"name": "Guayaquil",
"visitors": "40"
},
{
"name": "La Paz",
"visitors": "38"
},
{
"name": "San Jos\u00e9",
"visitors": "37"
},
{
"name": "Caracas",
"visitors": "35"
},
{
"name": "Gustavo Adolfo Madero",
"visitors": "30"
},
{
"name": "N/A",
"visitors": "30"
},
{
"name": "Puebla",
"visitors": "28"
},
{
"name": "Benito Juarez",
"visitors": "27"
},
{
"name": "Bucaramanga",
"visitors": "24"
},
{
"name": "Guadalajara",
"visitors": "24"
},
{
"name": "Montevideo",
"visitors": "23"
},
{
"name": "San Salvador",
"visitors": "23"
},
{
"name": "Guatemala City",
"visitors": "23"
},
{
"name": "Barranquilla",
"visitors": "23"
},
{
"name": "Panam\u00e1",
"visitors": "22"
},
{
"name": "Arequipa",
"visitors": "22"
},
{
"name": "Cali",
"visitors": "20"
},
{
"name": "La Plata",
"visitors": "19"
},
{
"name": "Santo Domingo",
"visitors": "19"
},
{
"name": "Managua",
"visitors": "19"
},
{
"name": "Valencia",
"visitors": "18"
},
{
"name": "M\u00e1laga",
"visitors": "18"
},
{
"name": "A Coru\u00f1a",
"visitors": "17"
},
{
"name": "Cartagena",
"visitors": "16"
},
{
"name": "Cochabamba",
"visitors": "16"
},
{
"name": "Iztapalapa",
"visitors": "15"
},
{
"name": "Barquisimeto",
"visitors": "15"
},
{
"name": "Portoviejo",
"visitors": "15"
},
{
"name": "Concepci\u00f3n",
"visitors": "15"
},
{
"name": "Oaxaca",
"visitors": "14"
},
{
"name": "Tijuana",
"visitors": "14"
},
{
"name": "Morelia",
"visitors": "14"
},
{
"name": "Zaragoza",
"visitors": "13"
},
{
"name": "Asunci\u00f3n",
"visitors": "13"
},
{
"name": "Tlalnepantla",
"visitors": "13"
},
{
"name": "N/A",
"visitors": "13"
},
{
"name": "Salta",
"visitors": "13"
},
{
"name": "Rosario",
"visitors": "13"
},
{
"name": "Gobernador Gregores",
"visitors": "13"
},
{
"name": "Singapore",
"visitors": "12"
},
{
"name": "\u00c1lvaro Obreg\u00f3n",
"visitors": "12"
},
{
"name": "Cuautitl\u00e1n Izcalli",
"visitors": "12"
},
{
"name": "M\u00e9rida",
"visitors": "12"
},
{
"name": "Coyoac\u00e1n",
"visitors": "12"
},
{
"name": "Santiago de Quer\u00e9taro",
"visitors": "12"
},
{
"name": "Le\u00f3n de los Aldama",
"visitors": "12"
},
{
"name": "Ciudad Ju\u00e1rez",
"visitors": "12"
},
{
"name": "Murcia",
"visitors": "11"
},
{
"name": "Valladolid",
"visitors": "11"
},
{
"name": "Lomas de Zamora",
"visitors": "11"
},
{
"name": "Cuernavaca",
"visitors": "11"
},
{
"name": "Havana",
"visitors": "11"
},
{
"name": "C\u00f3rdoba",
"visitors": "11"
},
{
"name": "La Serena",
"visitors": "11"
},
{
"name": "Zapopan",
"visitors": "11"
},
{
"name": "Monterrey",
"visitors": "11"
},
{
"name": "Miami",
"visitors": "11"
},
{
"name": "N/A",
"visitors": "11"
},
{
"name": "Vigo",
"visitors": "10"
},
{
"name": "Maracaibo",
"visitors": "10"
},
{
"name": "Bah\u00eda Blanca",
"visitors": "10"
},
{
"name": "Valpara\u00edso",
"visitors": "10"
},
{
"name": "Donostia / San Sebasti\u00e1n",
"visitors": "9"
},
{
"name": "Bilbao",
"visitors": "9"
},
{
"name": "Ecatepec de Morelos",
"visitors": "9"
},
{
"name": "Azcapotzalco",
"visitors": "9"
},
{
"name": "Manta",
"visitors": "9"
},
{
"name": "Miguel Hidalgo",
"visitors": "9"
},
{
"name": "Saltillo",
"visitors": "9"
},
{
"name": "Ensenada",
"visitors": "9"
},
{
"name": "Sevilla",
"visitors": "8"
},
{
"name": "Salamanca",
"visitors": "8"
},
{
"name": "Santiago de los Caballeros",
"visitors": "8"
},
{
"name": "Tegucigalpa",
"visitors": "8"
},
{
"name": "Trujillo",
"visitors": "8"
},
{
"name": "Piura",
"visitors": "8"
},
{
"name": "Cuauht\u00e9moc",
"visitors": "8"
},
{
"name": "Vi\u00f1a del Mar",
"visitors": "8"
},
{
"name": "Ahome",
"visitors": "8"
},
{
"name": "Santo Domingo Este",
"visitors": "8"
},
{
"name": "Quilmes",
"visitors": "7"
},
{
"name": "Coatzacoalcos",
"visitors": "7"
},
{
"name": "Ciudad Nezahualcoyotl",
"visitors": "7"
},
{
"name": "Villavicencio",
"visitors": "7"
},
{
"name": "Pasto",
"visitors": "7"
},
{
"name": "San Bernardo",
"visitors": "7"
},
{
"name": "Puente Alto",
"visitors": "7"
},
{
"name": "Zacatecas",
"visitors": "7"
},
{
"name": "Ciudad Apodaca",
"visitors": "7"
},
{
"name": "Alicante",
"visitors": "6"
},
{
"name": "Resistencia",
"visitors": "6"
},
{
"name": "Mar del Plata",
"visitors": "6"
},
{
"name": "San Pedro Sula",
"visitors": "6"
},
{
"name": "Ch\u00eda",
"visitors": "6"
},
{
"name": "Venustiano Carranza",
"visitors": "6"
},
{
"name": "Santa Fe",
"visitors": "6"
},
{
"name": "Santa Cruz de la Sierra",
"visitors": "6"
},
{
"name": "Beijing",
"visitors": "5"
},
{
"name": "Jerez de la Frontera",
"visitors": "5"
},
{
"name": "Granada",
"visitors": "5"
},
{
"name": "C\u00f3rdoba",
"visitors": "5"
},
{
"name": "Rivas-Vaciamadrid",
"visitors": "5"
},
{
"name": "Terrassa",
"visitors": "5"
},
{
"name": "Lleida",
"visitors": "5"
},
{
"name": "Chamart\u00edn",
"visitors": "5"
},
{
"name": "N/A",
"visitors": "5"
},
{
"name": "N/A",
"visitors": "5"
},
{
"name": "Tuxtla",
"visitors": "5"
},
{
"name": "Toluca",
"visitors": "5"
},
{
"name": "Nuevo Laredo",
"visitors": "5"
},
{
"name": "Naucalpan de Ju\u00e1rez",
"visitors": "5"
},
{
"name": "Metepec",
"visitors": "5"
},
{
"name": "C\u00f3rdoba",
"visitors": "5"
},
{
"name": "Coro",
"visitors": "5"
},
{
"name": "Santo Domingo de los Colorados",
"visitors": "5"
},
{
"name": "Cuenca",
"visitors": "5"
},
{
"name": "C\u00facuta",
"visitors": "5"
},
{
"name": "Iquitos",
"visitors": "5"
},
{
"name": "Chimbote",
"visitors": "5"
},
{
"name": "Matur\u00edn",
"visitors": "5"
},
{
"name": "R\u00edo Gallegos",
"visitors": "5"
},
{
"name": "R\u00edo Cuarto",
"visitors": "5"
},
{
"name": "Neuqu\u00e9n",
"visitors": "5"
},
{
"name": "Jos\u00e9 de San Mart\u00edn",
"visitors": "5"
},
{
"name": "Talca",
"visitors": "5"
},
{
"name": "N/A",
"visitors": "5"
},
{
"name": "Antofagasta",
"visitors": "5"
},
{
"name": "Tacna",
"visitors": "5"
},
{
"name": "Huancayo",
"visitors": "5"
},
{
"name": "Tlaquepaque",
"visitors": "5"
},
{
"name": "San Luis Potos\u00ed",
"visitors": "5"
},
{
"name": "Hermosillo",
"visitors": "5"
},
{
"name": "Guadalupe",
"visitors": "5"
},
{
"name": "Culiac\u00e1n",
"visitors": "5"
},
{
"name": "Athens",
"visitors": "4"
},
{
"name": "Shanghai",
"visitors": "4"
},
{
"name": "Santa Cruz de Tenerife",
"visitors": "4"
},
{
"name": "Las Palmas de Gran Canaria",
"visitors": "4"
},
{
"name": "Gasteiz / Vitoria",
"visitors": "4"
},
{
"name": "Barakaldo",
"visitors": "4"
},
{
"name": "Oviedo",
"visitors": "4"
},
{
"name": "Logro\u00f1o",
"visitors": "4"
},
{
"name": "Legan\u00e9s",
"visitors": "4"
},
{
"name": "Fuenlabrada",
"visitors": "4"
},
{
"name": "Milan",
"visitors": "4"
},
{
"name": "N/A",
"visitors": "4"
},
{
"name": "Berazategui",
"visitors": "4"
},
{
"name": "Azul",
"visitors": "4"
},
{
"name": "Xochimilco",
"visitors": "4"
},
{
"name": "Tlalpan",
"visitors": "4"
},
{
"name": "Tl\u00e1huac",
"visitors": "4"
},
{
"name": "Poza Rica de Hidalgo",
"visitors": "4"
},
{
"name": "Canc\u00fan",
"visitors": "4"
},
{
"name": "N/A",
"visitors": "4"
},
{
"name": "Valencia",
"visitors": "4"
},
{
"name": "Ciudad Guayana",
"visitors": "4"
},
{
"name": "Pereira",
"visitors": "4"
},
{
"name": "Monter\u00eda",
"visitors": "4"
},
{
"name": "Manizales",
"visitors": "4"
},
{
"name": "Chiclayo",
"visitors": "4"
},
{
"name": "Yerba Buena",
"visitors": "4"
},
{
"name": "Paran\u00e1",
"visitors": "4"
},
{
"name": "Concepci\u00f3n",
"visitors": "4"
},
{
"name": "Temuco",
"visitors": "4"
},
{
"name": "N/A",
"visitors": "4"
},
{
"name": "Iquique",
"visitors": "4"
},
{
"name": "San Clemente",
"visitors": "4"
},
{
"name": "Ocotl\u00e1n",
"visitors": "4"
},
{
"name": "Victoria de Durango",
"visitors": "4"
},
{
"name": "Aguascalientes",
"visitors": "4"
},
{
"name": "New York City",
"visitors": "4"
},
{
"name": "Las Vegas",
"visitors": "4"
},
{
"name": "Avellaneda",
"visitors": "4"
},
{
"name": "N/A",
"visitors": "4"
},
{
"name": "Guangzhou",
"visitors": "3"
},
{
"name": "Suzhou",
"visitors": "3"
},
{
"name": "Talavera de la Reina",
"visitors": "3"
},
{
"name": "La Laguna",
"visitors": "3"
},
{
"name": "Onda",
"visitors": "3"
},
{
"name": "Castell\u00f3 de la Plana",
"visitors": "3"
},
{
"name": "And\u00fajar",
"visitors": "3"
},
{
"name": "Valdemoro",
"visitors": "3"
},
{
"name": "Santiago de Compostela",
"visitors": "3"
},
{
"name": "Pozuelo de Alarc\u00f3n",
"visitors": "3"
},
{
"name": "Pamplona",
"visitors": "3"
},
{
"name": "M\u00f3stoles",
"visitors": "3"
},
{
"name": "Le\u00f3n",
"visitors": "3"
},
{
"name": "Las Rozas de Madrid",
"visitors": "3"
},
{
"name": "Guadalajara",
"visitors": "3"
},
{
"name": "Collado-Villalba",
"visitors": "3"
},
{
"name": "Badalona",
"visitors": "3"
},
{
"name": "Alcal\u00e1 de Henares",
"visitors": "3"
},
{
"name": "Oslo",
"visitors": "3"
},
{
"name": "San Justo",
"visitors": "3"
},
{
"name": "Merlo",
"visitors": "3"
},
{
"name": "N/A",
"visitors": "3"
},
{
"name": "Lan\u00fas",
"visitors": "3"
},
{
"name": "Ituzaing\u00f3",
"visitors": "3"
},
{
"name": "Formosa",
"visitors": "3"
},
{
"name": "Corrientes",
"visitors": "3"
},
{
"name": "Concordia",
"visitors": "3"
},
{
"name": "Maldonado",
"visitors": "3"
},
{
"name": "Zumpango",
"visitors": "3"
},
{
"name": "Santa Cruz Xoxocotl\u00e1n",
"visitors": "3"
},
{
"name": "Reynosa",
"visitors": "3"
},
{
"name": "Nicol\u00e1s Romero",
"visitors": "3"
},
{
"name": "Xalapa de Enr\u00edquez",
"visitors": "3"
},
{
"name": "Ciudad L\u00f3pez Mateos",
"visitors": "3"
},
{
"name": "San Pedro",
"visitors": "3"
},
{
"name": "Maracay",
"visitors": "3"
},
{
"name": "Los Teques",
"visitors": "3"
},
{
"name": "Samborond\u00f3n",
"visitors": "3"
},
{
"name": "Quevedo",
"visitors": "3"
},
{
"name": "Ibarra",
"visitors": "3"
},
{
"name": "Yopal",
"visitors": "3"
},
{
"name": "Santa Marta",
"visitors": "3"
},
{
"name": "Bello",
"visitors": "3"
},
{
"name": "Pucallpa",
"visitors": "3"
},
{
"name": "Tlaxcala",
"visitors": "3"
},
{
"name": "N/A",
"visitors": "3"
},
{
"name": "Villa Constituci\u00f3n",
"visitors": "3"
},
{
"name": "Tres Arroyos",
"visitors": "3"
},
{
"name": "Santa Rosa",
"visitors": "3"
},
{
"name": "San Luis",
"visitors": "3"
},
{
"name": "Las Varillas",
"visitors": "3"
},
{
"name": "Jun\u00edn",
"visitors": "3"
},
{
"name": "N/A",
"visitors": "3"
},
{
"name": "Ica",
"visitors": "3"
},
{
"name": "Cusco",
"visitors": "3"
},
{
"name": "Santa Catarina",
"visitors": "3"
},
{
"name": "San Nicol\u00e1s de los Garza",
"visitors": "3"
},
{
"name": "Salamanca",
"visitors": "3"
},
{
"name": "Mexicali",
"visitors": "3"
},
{
"name": "Mazatl\u00e1n",
"visitors": "3"
},
{
"name": "Irapuato",
"visitors": "3"
},
{
"name": "Guadalupe Trujillo",
"visitors": "3"
},
{
"name": "Chihuahua",
"visitors": "3"
},
{
"name": "Reston",
"visitors": "3"
},
{
"name": "San Miguel",
"visitors": "3"
},
{
"name": "N/A",
"visitors": "3"
},
{
"name": "Riyadh",
"visitors": "2"
},
{
"name": "R\u00e2mnicu V\u00e2lcea",
"visitors": "2"
},
{
"name": "Bucharest",
"visitors": "2"
},
{
"name": "Warsaw",
"visitors": "2"
},
{
"name": "Patna",
"visitors": "2"
},
{
"name": "Ho Chi Minh City",
"visitors": "2"
},
{
"name": "Shijiazhuang",
"visitors": "2"
},
{
"name": "Hangzhou",
"visitors": "2"
},
{
"name": "Fuyang",
"visitors": "2"
},
{
"name": "Dalian",
"visitors": "2"
},
{
"name": "Chengdu",
"visitors": "2"
},
{
"name": "Amadora",
"visitors": "2"
},
{
"name": "Villarejo de Fuentes",
"visitors": "2"
},
{
"name": "Torrevieja",
"visitors": "2"
},
{
"name": "San Vicent del Raspeig",
"visitors": "2"
},
{
"name": "San Juan de Aznalfarache",
"visitors": "2"
},
{
"name": "Roquetas de Mar",
"visitors": "2"
},
{
"name": "Pilar de la Horadada",
"visitors": "2"
},
{
"name": "Ontinyent",
"visitors": "2"
},
{
"name": "Mairena del Aljarafe",
"visitors": "2"
},
{
"name": "Lucena",
"visitors": "2"
},
{
"name": "La Rambla",
"visitors": "2"
},
{
"name": "Elche",
"visitors": "2"
},
{
"name": "Crevillente",
"visitors": "2"
},
{
"name": "Castilleja de la Cuesta",
"visitors": "2"
},
{
"name": "Cartagena",
"visitors": "2"
},
{
"name": "Benifai\u00f3",
"visitors": "2"
},
{
"name": "Arona",
"visitors": "2"
},
{
"name": "Almer\u00eda",
"visitors": "2"
},
{
"name": "Alfafar",
"visitors": "2"
},
{
"name": "Pa\u00e7os de Ferreira",
"visitors": "2"
},
{
"name": "Naaldwijk",
"visitors": "2"
},
{
"name": "Amsterdam",
"visitors": "2"
},
{
"name": "Luxembourg",
"visitors": "2"
},
{
"name": "Arras",
"visitors": "2"
},
{
"name": "Villaviciosa de Od\u00f3n",
"visitors": "2"
},
{
"name": "Villanueva de la Ca\u00f1ada",
"visitors": "2"
},
{
"name": "Tudela",
"visitors": "2"
},
{
"name": "Cerdanyola del Vall\u00e8s",
"visitors": "2"
},
{
"name": "Santander",
"visitors": "2"
},
{
"name": "Sabadell",
"visitors": "2"
},
{
"name": "Reus",
"visitors": "2"
},
{
"name": "Pontevedra",
"visitors": "2"
},
{
"name": "N/A",
"visitors": "2"
},
{
"name": "Parla",
"visitors": "2"
},
{
"name": "Palencia",
"visitors": "2"
},
{
"name": "Majadahonda",
"visitors": "2"
},
{
"name": "Loeches",
"visitors": "2"
},
{
"name": "Irun",
"visitors": "2"
},
{
"name": "L'Hospitalet de Llobregat",
"visitors": "2"
}
]