[
{
"name": "Chrome",
"visitors": "4404"
},
{
"name": "Microsoft Edge",
"visitors": "3384"
},
{
"name": "Safari",
"visitors": "329"
},
{
"name": "Mobile App",
"visitors": "309"
},
{
"name": "Firefox",
"visitors": "275"
},
{
"name": "Smart Lenovo Browser",
"visitors": "122"
},
{
"name": "Quark",
"visitors": "119"
},
{
"name": "QQ Browser",
"visitors": "103"
},
{
"name": "UC Browser",
"visitors": "74"
},
{
"name": "vivo Browser",
"visitors": "45"
},
{
"name": "Huawei Browser Mobile",
"visitors": "43"
},
{
"name": "MIUI Browser",
"visitors": "43"
},
{
"name": "Sogou Explorer",
"visitors": "34"
},
{
"name": "Opera",
"visitors": "10"
},
{
"name": "Huawei Browser",
"visitors": "8"
},
{
"name": "(not set)",
"visitors": "5"
},
{
"name": "Samsung Browser",
"visitors": "2"
},
{
"name": "Yandex Browser",
"visitors": "2"
},
{
"name": "115 Browser",
"visitors": "1"
},
{
"name": "360 Secure Browser",
"visitors": "1"
},
{
"name": "Android Browser",
"visitors": "1"
},
{
"name": "Vivaldi",
"visitors": "1"
},
{
"name": "Whale Browser",
"visitors": "1"
}
]